cognite/model_hosting/notebook/__init__.py
cognite/model_hosting/notebook/_model_file.py
cognite/model_hosting/notebook/_setup_file.py
cognite/model_hosting/notebook/notebook.py
cognite_model_hosting_notebook-0.2.0.dist-info/METADATA
cognite_model_hosting_notebook-0.2.0.dist-info/WHEEL
cognite_model_hosting_notebook-0.2.0.dist-info/top_level.txt
cognite_model_hosting_notebook-0.2.0.dist-info/RECORD
