Metadata-Version: 2.1
Name: cognite-model-hosting-notebook
Version: 0.2.0
Summary: Deploy notebooks to Cognite's model hosting environment
Home-page: UNKNOWN
Author: Nils Barlaug
Author-email: nils.barlaug@cognite.com
License: UNKNOWN
Platform: UNKNOWN
Requires-Python: >=3.5
Requires-Dist: cognite-sdk (<2.0.0,>=1.4.0)
Requires-Dist: requests
